mod.json
gradle/libs.versions.toml
hexdoc_hexbound/__gradle_version__.py
hexdoc_hexbound/__init__.py
hexdoc_hexbound/__version__.py
hexdoc_hexbound/_hooks.py
hexdoc_hexbound/py.typed
hexdoc_hexbound/_export/.gitignore
hexdoc_hexbound/_export/__init__.py
hexdoc_hexbound/_export/generated/__init__.py
hexdoc_hexbound/_export/generated/hexbound.hexdoc.json
hexdoc_hexbound/_export/generated/hexbound.patterns.hexdoc.json
hexdoc_hexbound/_export/generated/assets/hexbound/lang/en_us.flatten.json5
hexdoc_hexbound/_export/generated/assets/hexbound/lang/zh_cn.flatten.json5
hexdoc_hexbound/_export/generated/assets/hexbound/models/block/construct_broadcaster/on.json
hexdoc_hexbound/_export/generated/assets/hexbound/models/item/construct_broadcaster.json
hexdoc_hexbound/_export/generated/assets/hexbound/models/item/spider_construct_battery.json
hexdoc_hexbound/_export/generated/assets/hexbound/models/item/spider_construct_core.json
hexdoc_hexbound/_export/generated/assets/hexbound/textures/block/construct_broadcaster/back.png
hexdoc_hexbound/_export/generated/assets/hexbound/textures/block/construct_broadcaster/bottom.png
hexdoc_hexbound/_export/generated/assets/hexbound/textures/block/construct_broadcaster/left.png
hexdoc_hexbound/_export/generated/assets/hexbound/textures/block/construct_broadcaster/right.png
hexdoc_hexbound/_export/generated/assets/hexbound/textures/block/construct_broadcaster/off/front.png
hexdoc_hexbound/_export/generated/assets/hexbound/textures/block/construct_broadcaster/off/top.png
hexdoc_hexbound/_export/generated/assets/hexbound/textures/block/construct_broadcaster/on/front.png
hexdoc_hexbound/_export/generated/assets/hexbound/textures/block/construct_broadcaster/on/top.png
hexdoc_hexbound/_export/generated/assets/hexbound/textures/combat/shield.png
hexdoc_hexbound/_export/generated/assets/hexbound/textures/construct/robot_construct.png
hexdoc_hexbound/_export/generated/assets/hexbound/textures/construct/robot_construct_translucent.png
hexdoc_hexbound-0.1.4.1.19.2.1.0.dev2.dist-info/METADATA
hexdoc_hexbound-0.1.4.1.19.2.1.0.dev2.dist-info/WHEEL
hexdoc_hexbound-0.1.4.1.19.2.1.0.dev2.dist-info/entry_points.txt
hexdoc_hexbound-0.1.4.1.19.2.1.0.dev2.dist-info/licenses/LICENSE
hexdoc_hexbound-0.1.4.1.19.2.1.0.dev2.dist-info/RECORD
