Metadata-Version: 2.3
Name: hexdoc-hexbound
Version: 0.1.4.1.19.2.1.0.dev2
Summary: Python web book docgen and hexdoc plugin for Hexbound.
Project-URL: Homepage, https://hexbound.hexxy.media
Project-URL: Source, https://github.com/object-Object/hexbound
Author: Cypher121
Maintainer: object-Object
License-File: LICENSE
Keywords: hexdoc
Requires-Python: >=3.11
Requires-Dist: hexdoc-hexal~=0.2.19.1.0.dev0
Requires-Dist: hexdoc-hexcasting~=0.10.3.1.0
Requires-Dist: hexdoc>=1!0.1.0a18
Provides-Extra: dev
Requires-Dist: ruff~=0.1.4; extra == 'dev'
